levels/__init__.py
levels/levels.py
logiliteal/__init__.py
logiliteal/levels/__init__.py
logiliteal/levels/levels.py
logiliteal/utils/__init__.py
logiliteal/utils/configs.py
logiliteal/utils/fmt.py
logiliteal/utils/placeholder.py
logiliteal/utils/regex.py
logiliteal/utils/styles.py
logiliteal/utils/time.py
logiliteal-0.1.4.dist-info/licenses/LICENSE
utils/__init__.py
utils/configs.py
utils/fmt.py
utils/styles.py
utils/time.py
logiliteal-0.1.4.dist-info/METADATA
logiliteal-0.1.4.dist-info/WHEEL
logiliteal-0.1.4.dist-info/top_level.txt
logiliteal-0.1.4.dist-info/RECORD
