Metadata-Version: 2.4
Name: logiliteal
Version: 0.1.4
Summary: 简洁,高扩展性,可自定义的日志库 / Simple, high extensibility, and customizable logging library
Home-page: https://github.com/Nanaloveyuki/py-logiliteal
Author: Nanaloveyuki
Author-email: 3541766758@qq.com
License: MIT
Project-URL: Bug Reports, https://github.com/Nanaloveyuki/py-logiliteal/issues
Project-URL: Source, https://github.com/Nanaloveyuki/py-logiliteal/
Keywords: logging,color,format
Classifier: Topic :: Software Development :: Libraries :: Python Modules
Classifier: Development Status :: 4 - Beta
Classifier: Intended Audience :: Developers
Classifier: Programming Language :: Python :: 3.12
Classifier: Programming Language :: Python :: 3.13
Classifier: Operating System :: OS Independent
Requires-Python: >=3.12, <4
License-File: LICENSE
Dynamic: author
Dynamic: author-email
Dynamic: classifier
Dynamic: description
Dynamic: description-content-type
Dynamic: home-page
Dynamic: keywords
Dynamic: license
Dynamic: license-file
Dynamic: project-url
Dynamic: requires-python
Dynamic: summary
